main.py
mcp_server_coding-0.1.1.dist-info/METADATA
mcp_server_coding-0.1.1.dist-info/WHEEL
mcp_server_coding-0.1.1.dist-info/entry_points.txt
mcp_server_coding-0.1.1.dist-info/top_level.txt
mcp_server_coding-0.1.1.dist-info/RECORD
