Metadata-Version: 2.4
Name: mcp-server-coding
Version: 0.1.1
Summary: Add your description here
Requires-Python: >=3.13
Requires-Dist: mcp[cli]>=1.13.1
Requires-Dist: requests>=2.31.0
